ejahdilandatastruct/__init__.py
ejahdilandatastruct/arrays.py
ejahdilandatastruct/graph.py
ejahdilandatastruct/linked_lists.py
ejahdilandatastruct/queue.py
ejahdilandatastruct/stack.py
ejahdilandatastruct/tree.py
ejahdilandatastruct-0.1.1.dist-info/licenses/LICENSE
ejahdilandatastruct-0.1.1.dist-info/METADATA
ejahdilandatastruct-0.1.1.dist-info/WHEEL
ejahdilandatastruct-0.1.1.dist-info/top_level.txt
ejahdilandatastruct-0.1.1.dist-info/RECORD
