Metadata-Version: 2.4
Name: ejahdilandatastruct
Version: 0.1.1
Summary: A pedagogical Python package implementing core data structures from scratch
Author-email: Ejah Dilan <ejahdilan58@gmail.com>
License: MIT
Project-URL: homepage, https://github.com/EjahDil/data-structures-python
Project-URL: repository, https://github.com/EjahDil/data-structures-python
Keywords: data structures,algorithms,python,education
Classifier: Programming Language :: Python :: 3
Classifier: Programming Language :: Python :: 3.6
Classifier: Programming Language :: Python :: 3.7
Classifier: Programming Language :: Python :: 3.8
Classifier: Programming Language :: Python :: 3.9
Classifier: License :: OSI Approved :: MIT License
Classifier: Intended Audience :: Developers
Classifier: Intended Audience :: Education
Classifier: Programming Language :: Python :: Implementation :: CPython
Classifier: Operating System :: OS Independent
License-File: LICENSE
Dynamic: license-file
